errorex/__init__.py
errorex/formatter.py
errorex/logger.py
errorex/main.py
errorex/suggester.py
errorex-0.1.0.dist-info/METADATA
errorex-0.1.0.dist-info/WHEEL
errorex-0.1.0.dist-info/top_level.txt
errorex-0.1.0.dist-info/RECORD
