Metadata-Version: 2.4
Name: errorex
Version: 0.1.0
Summary: A Python library for explaining and debugging errors in ML/data pipelines with variable snapshots and LLM-ready prompts.
Home-page: https://github.com/minalbansal14/errorex
Author: Minal Bansal
Classifier: Programming Language :: Python :: 3
Classifier: License :: OSI Approved :: MIT License
Classifier: Operating System :: OS Independent
Classifier: Intended Audience :: Developers
Classifier: Topic :: Software Development :: Debuggers
Requires-Python: >=3.7
Requires-Dist: rich
Dynamic: author
Dynamic: classifier
Dynamic: description
Dynamic: description-content-type
Dynamic: home-page
Dynamic: requires-dist
Dynamic: requires-python
Dynamic: summary
